MANIFEST.in
Makefile
README
setup.py
test/__init__.py
test/__init__.pyc
test/fixtures.py
test/fixtures.pyc
test/test_csv.py
test/test_csv.pyc
test/test_import_csv.py
test/test_import_csv.pyc
tiddlywebplugins/__init__.py
tiddlywebplugins/csv.py
tiddlywebplugins.csv.egg-info/PKG-INFO
tiddlywebplugins.csv.egg-info/SOURCES.txt
tiddlywebplugins.csv.egg-info/dependency_links.txt
tiddlywebplugins.csv.egg-info/namespace_packages.txt
tiddlywebplugins.csv.egg-info/not-zip-safe
tiddlywebplugins.csv.egg-info/requires.txt
tiddlywebplugins.csv.egg-info/top_level.txt