Metadata-Version: 1.0
Name: tiddlywebplugins.csv
Version: 0.5
Summary: A csv serializer for TiddlyWeb
Home-page: http://pypi.python.org/pypi/tiddlywebplugins.csv
Author: Ben Gillies
Author-email: bengillies@gmail.com
License: UNKNOWN
Platform: Posix; MacOS X; Windows
